greener_agent/__init__.py
greener_agent-0.0.1.dist-info/licenses/LICENSE
greener_agent-0.0.1.dist-info/METADATA
greener_agent-0.0.1.dist-info/WHEEL
greener_agent-0.0.1.dist-info/top_level.txt
greener_agent-0.0.1.dist-info/RECORD
