Metadata-Version: 2.4
Name: greener-agent
Version: 0.0.1
Summary: Greener Agent
Home-page: https://greener.cephei8.onl
Author: cephei8
Author-email: i@cephei8.onl
Classifier: Programming Language :: Python :: 3
Requires-Python: >=3.7, <4
License-File: LICENSE
Dynamic: author
Dynamic: author-email
Dynamic: classifier
Dynamic: description
Dynamic: description-content-type
Dynamic: home-page
Dynamic: license-file
Dynamic: requires-python
Dynamic: summary
